mon_projet/__init__.py
mon_projet/main.py
mon_projet/config/__init__.py
mon_projet/config/settings.py
mon_projet/domain/__init__.py
mon_projet/domain/exceptions.py
mon_projet/domain/models.py
mon_projet/domain/services.py
mon_projet/infrastructure/__init__.py
mon_projet/infrastructure/notifications.py
mon_projet/infrastructure/persistence.py
mon_projet/utils/__init__.py
mon_projet/utils/helpers.py
gestion_benefices_magasin-0.1.0.dist-info/METADATA
gestion_benefices_magasin-0.1.0.dist-info/WHEEL
gestion_benefices_magasin-0.1.0.dist-info/top_level.txt
gestion_benefices_magasin-0.1.0.dist-info/RECORD
