Metadata-Version: 2.4
Name: gestion_benefices_magasin
Version: 0.1.0
Summary: Application Python orientée objet pour calculer les bénéfices des ventes d'un magasin
Author-email: Jassen <jasseneugene@gmail.com>
Requires-Python: >=3.10
Provides-Extra: dev
Requires-Dist: pytest>=7.0; extra == "dev"
